pizzapy/__init__.py
pizzapy/__main__.py
pizzapy-0.0.0.dist-info/LICENSE
pizzapy-0.0.0.dist-info/METADATA
pizzapy-0.0.0.dist-info/WHEEL
pizzapy-0.0.0.dist-info/entry_points.txt
pizzapy-0.0.0.dist-info/top_level.txt
pizzapy-0.0.0.dist-info/RECORD
